{
    "title":"Symbol",
    "rules":[
        {
            "description":"R_command + qwdrgjuivp to !@#$%^&*()",
            "manipulators":[
				{
					"type":"basic",
					"from":{
						"key_code":"q",
						"modifiers":{
							"mandatory":["right_command"],
							"optional":[
								"caps_lock",
								"shift"
							]
						}
					},
					"to":[
						{
							"key_code":"1",
							"modefiers":"shift"
						}
					]
				},
				{
					"type":"basic",
					"from":{
						"key_code":"w",
						"modifiers":{
							"mandatory":["right_command"],
							"optional":[
								"caps_lock",
								"shift"
							]
						}
					},
					"to":[
						{
							"key_code":"2",
							"modefiers":"shift"
						}
					]
				},
				{
					"type":"basic",
					"from":{
						"key_code":"e",
						"modifiers":{
							"mandatory":["right_command"],
							"optional":[
								"caps_lock",
								"shift"
							]
						}
					},
					"to":[
						{
							"key_code":"3",
							"modifiers":"shift"
						}
					]
				},
				{
					"type":"basic",
					"from":{
						"key_code":"r",
						"modifiers":{
							"mandatory":["right_command"],
							"optional":[
								"caps_lock",
								"shift"
							]
						}
					},
					"to":[
						{
							"key_code":"4",
							"modifiers":"shift"
						}
					]
				},
				{
					"type":"basic",
					"from":{
						"key_code":"t",
						"modifiers":{
							"mandatory":["right_command"],
							"optional":[
								"caps_lock",
								"shift"
							]
						}
					},
					"to":[
						{
							"key_code":"5",
							"modifiers":"shift"
						}
					]
				},
				{
					"type":"basic",
					"from":{
						"key_code":"y",
						"modifiers":{
							"mandatory":["right_command"],
							"optional":[
								"caps_lock",
								"shift"
							]
						}
					},
					"to":[
						{
							"key_code":"6",
							"modifiers":"shift"
						}
					]
				},
				{
					"type":"basic",
					"from":{
						"key_code":"u",
						"modifiers":{
							"mandatory":["right_command"],
							"optional":[
								"caps_lock",
								"shift"
							]
						}
					},
					"to":[
						{
							"key_code":"7",
							"modifiers":"shift"
						}
					]
				},
				{
					"type":"basic",
					"from":{
						"key_code":"i",
						"modifiers":{
							"mandatory":["right_command"],
							"optional":[
								"caps_lock",
								"shift"
							]
						}
					},
					"to":[
						{
							"key_code":"8",
							"modifiers":"shift"
						}
					]
				},
				{
					"type":"basic",
					"from":{
						"key_code":"o",
						"modifiers":{
							"mandatory":["right_command"],
							"optional":[
								"caps_lock",
								"shift"
							]
						}
					},
					"to":[
						{
							"key_code":"9",
							"modifiers":"shift"
						}
					]
				},
				{
					"type":"basic",
					"from":{
						"key_code":"p",
						"modifiers":{
							"mandatory":["right_command"],
							"optional":[
								"caps_lock",
								"shift"
							]
						}
					},
					"to":[
						{
							"key_code":"0",
							"modifiers":"shift"
						}
					]
				}
			]
    }
  ]
}